<?xml version='1.0' encoding='utf-8'?>
<patentes>
  <patente id="1" type="Patente - Invención">
    <title>
      <text lang="es" country="CO">Composición de Oligopéptidos Diseñados a Partir de Secuencias de los Alergenos del Grupo 1 de Ácaros Intradomiciliarios</text>
      </title>
    <description>
      <text lang="es" country="CO">Oligopeptidos sinteticos diseñados a partir de cisteinproteasas de acaros y metodos para la produccion de anticuerpos policlonales igy para la deteccion de acaros intradomiciliarios.</text>
      </description>
    <jurisdiccion>Colombia</jurisdiccion>
    <numeroSolicitud>9027540</numeroSolicitud>
    </patente>
  <patente id="2" type="Patente - PCT">
    <title>
      <text lang="es" country="CO">Oligopéptidos sintéticos diseñados a partir de cisteinproteasas de ácaros y método para la producción de anticuerpos policlonales IgY para la detección de ácaros intradomiciliarios</text>
      </title>
    <description>
      <text lang="es" country="CO">Oligopeptidos sinteticos diseñados a partir de cisteinproteasas de acaros y metodos para la produccion de anticuerpos policlonales igy para la deteccion de acaros intradomiciliarios.</text>
      </description>
    <jurisdiccion>PCT</jurisdiccion>
    <numeroSolicitud>PCT/IB2010/000554 
WO/2010/146425</numeroSolicitud>
    </patente>
  <patente id="3" type="Patente - Invención">
    <title>
      <text lang="es" country="CO">Oligopeptidos sinteticos diseñados a partir de cisteinproteasas de acaros y metodos para la produccion de anticuerpos policlonales igy para la deteccion de acaros intradomiciliarios.</text>
      </title>
    <description>
      <text lang="es" country="CO">Oligopeptidos sinteticos diseñados a partir de cisteinproteasas de acaros y metodos para la produccion de anticuerpos policlonales igy para la deteccion de acaros intradomiciliarios.</text>
      </description>
    <jurisdiccion>México</jurisdiccion>
    <numeroSolicitud>MX/a/2011/009862

Número de registro: 345018</numeroSolicitud>
    </patente>
  <patente id="4" type="Patente - Invención">
    <title>
      <text lang="en" country="US">"Synthetic oligopeptides designed from mite cysteine proteases and methods for the production of IGY POLYCLONAL ANTIBODIES FOR THE DETECTION OF INTRADOMICILIARY MITES"</text>
      </title>
    <description>
      <text lang="es" country="CO">Oligopeptidos sinteticos diseñados a partir de cisteinproteasas de acaros y metodos para la produccion de anticuerpos policlonales igy para la deteccion de acaros intradomiciliarios.</text>
      </description>
    <jurisdiccion>Estados Unidos</jurisdiccion>
    <numeroSolicitud>13256918</numeroSolicitud>
    </patente>
  <patente id="5" type="Patente - Invención">
    <title>
      <text lang="de" country="US">OLIGOPEPTIDOS SINTETICOS DISEÑADOS A PARTIR DE CISTEINPROTEASAS DE ACAROS Y METODOS PARA LA PRODUCCION DE ANTICUERPOS POLICLONALES IGY PARA LA DETECCION DE
ACAROS INTRADCMICILIAR/OS.</text>
      </title>
    <description>
      <text lang="es" country="CO">Oligopeptidos sinteticos diseñados a partir de cisteinproteasas de acaros y metodos para la produccion de anticuerpos policlonales igy para la deteccion de acaros intradomiciliarios.</text>
      </description>
    <jurisdiccion>España</jurisdiccion>
    <numeroSolicitud>EP2431381</numeroSolicitud>
    </patente>
  <patente id="6" type="Patente - Invención">
    <title>
      <text lang="es" country="CO">Método y composición inmunoquímica para la detección de alérgenos  de ácaros usando anticuerpos policlonales IgY</text>
      </title>
    <description>
      <text lang="es" country="CO">Oligopeptidos sinteticos diseñados a partir de cisteinproteasas de acaros y metodos para la produccion de anticuerpos policlonales igy para la deteccion de acaros intradomiciliarios.</text>
      </description>
    <jurisdiccion>Colombia</jurisdiccion>
    <numeroSolicitud>10-24590</numeroSolicitud>
    </patente>
  <patente id="9" type="Registro de Software">
    <title>
      <text lang="fi" country="US">Sin título</text>
      </title>
    <description>
      <text lang="es" country="CO">Plataforma web de biología computaciónal que simplifica los análisis metabólicos de células neuronales.</text>
      </description>
    <jurisdiccion>Desconocido</jurisdiccion>
    </patente>
  <patente id="10" type="Registro de Software">
    <title>
      <text lang="es" country="CO">Juego Reto CODIFICO</text>
      </title>
    <description>
      <text lang="es" country="CO">APP     CODIFICO®     2.0     es     una     aplicación    móvil tipo juego, que puede ser descargada a los dispositivos con sistemas operativos   Android  y  IOS,  que a  partir  del  estudio  de  casos  enseña  la  forma  correcta  de  interpretar  los  signos  y  síntomas de una enfermedad   codificando los   diagnósticos  de  los  pacientes  bajo el sistema internacional CIE-10</text>
      </description>
    <jurisdiccion>Colombia</jurisdiccion>
    <numeroSolicitud>1366347</numeroSolicitud>
    </patente>
  <patente id="11" type="Marca Nominativa">
    <title>
      <text lang="pt" country="US">CODIFICO (9, 35, 41, 42)</text>
      </title>
    <description>
      <text lang="es" country="CO">APP     CODIFICO®     2.0     es     una     aplicación    móvil tipo juego, que puede ser descargada a los dispositivos con sistemas operativos   Android  y  IOS,  que a  partir  del  estudio  de  casos  enseña  la  forma  correcta  de  interpretar  los  signos  y  síntomas de una enfermedad   codificando los   diagnósticos  de  los  pacientes  bajo el sistema internacional CIE-10</text>
      </description>
    <jurisdiccion>Colombia</jurisdiccion>
    <numeroSolicitud>SD2018/0100344</numeroSolicitud>
    </patente>
  <patente id="13" type="Patente - Invención">
    <title>
      <text lang="es" country="CO">Avión no tripulado para inspección de infraestructuras</text>
      </title>
    <description>
      <text lang="es" country="CO">Avión no tripulado para inspección de infraestructuras</text>
      </description>
    <jurisdiccion>Colombia</jurisdiccion>
    <numeroSolicitud>15-243027</numeroSolicitud>
    </patente>
  <patente id="14" type="Patente - Invención">
    <title>
      <text lang="es" country="CO">Consorcio de hongos inmovilizados sobre un portador laminar de lignocelulosa para el tratamiento de aguas residuales y proceso para la elaboración del mismo</text>
      </title>
    <description>
      <text lang="es" country="CO">Consorcio de hongos inmovilizados sobre un portador laminar de lignocelulosa para el tratamiento de aguas residuales y proceso para la elaboración del mismo</text>
      </description>
    <jurisdiccion>Colombia</jurisdiccion>
    <numeroSolicitud>13-290121</numeroSolicitud>
    </patente>
  <patente id="16" type="Patente - Invención">
    <title>
      <text lang="es" country="CO">Método Biodirigido Para Preparar Una Fracción Bioactiva de Petiveria Alliacea y Composición Farmacéutica que Contiene Dicha Fracción Bioactiva</text>
      </title>
    <description>
      <text lang="es" country="CO">Phairilab es un conjunto de invenciones desarrolladas a partir de las propiedades funcionales de las plantas DIvidivi y Anamú que tienen características especiales para desarrollar productos dermocosméticos, suplementos alimenticios  y fitomedicamentos para el tratamiento de pacientes con cancer.</text>
      </description>
    <jurisdiccion>Colombia</jurisdiccion>
    <numeroSolicitud>09-108636</numeroSolicitud>
    </patente>
  <patente id="17" type="Patente - Invención">
    <title>
      <text lang="en" country="US">Combination of Compounds Derived from Gallic Acid for the Treatment of Cancer</text>
      </title>
    <description>
      <text lang="es" country="CO">Phairilab es un conjunto de invenciones desarrolladas a partir de las propiedades funcionales de las plantas DIvidivi y Anamú que tienen características especiales para desarrollar productos dermocosméticos, suplementos alimenticios  y fitomedicamentos para el tratamiento de pacientes con cancer.</text>
      </description>
    <jurisdiccion>Estados Unidos</jurisdiccion>
    <numeroSolicitud>14/427.552</numeroSolicitud>
    </patente>
  <patente id="19" type="Patente - Invención">
    <title>
      <text lang="en" country="US">Pharmacological Chaperones for the enzyme N-acetylgalactosamine-6-sulfate sulfatase (GALNS) as treatment for Lysosomal Storage Diseases</text>
      </title>
    <description>
      <text lang="es" country="CO">Es un medicamento de segundo uso, es decir sirve para tratar dos condiciones. El uso desarrolado en la PUJ es para tratar la enfermedad de morquio, que es una enfermedad de nacimiento donde no se desarrollan los músculos y se tienen deficiencias neuronales.</text>
      </description>
    <jurisdiccion>Estados Unidos</jurisdiccion>
    <numeroSolicitud>62418734</numeroSolicitud>
    </patente>
  <patente id="20" type="Registro de Software">
    <title>
      <text lang="en" country="US">Checking Design Académico</text>
      </title>
    <description>
      <text lang="es" country="CO">Checking Design es un aplicativo web de autodiagnóstico en gestión de diseño y desarrollo de producto, el cual contiene diferentes herramientas que ayudan a realizar: Autodiagnóstico, definición estratégica de producto, conceptualización, pre-producción, y pre-comercialización, permitiendo identificar el estado de inserción del diseño al interior de sus organizaciones. Gracias a la aplicación de las herramientas de Checking Design, obtendrá un mapa de ruta para aumentar y mejorar el desarrollo de productos innovadores, a través de una adecuada gestión del diseño, logrando mejorar la competitividad de su organización.</text>
      </description>
    <jurisdiccion>Colombia</jurisdiccion>
    <numeroSolicitud>1. Académico (1366356)</numeroSolicitud>
    </patente>
  <patente id="21" type="Registro de Software">
    <title>
      <text lang="en" country="US">Checking Design Sectorial</text>
      </title>
    <description>
      <text lang="es" country="CO">Checking Design es un aplicativo web de autodiagnóstico en gestión de diseño y desarrollo de producto, el cual contiene diferentes herramientas que ayudan a realizar: Autodiagnóstico, definición estratégica de producto, conceptualización, pre-producción, y pre-comercialización, permitiendo identificar el estado de inserción del diseño al interior de sus organizaciones. Gracias a la aplicación de las herramientas de Checking Design, obtendrá un mapa de ruta para aumentar y mejorar el desarrollo de productos innovadores, a través de una adecuada gestión del diseño, logrando mejorar la competitividad de su organización.</text>
      </description>
    <jurisdiccion>Colombia</jurisdiccion>
    <numeroSolicitud>2. Sectorial (1366355)</numeroSolicitud>
    </patente>
  <patente id="22" type="Registro de Software">
    <title>
      <text lang="en" country="US">Checking Design Empresarial</text>
      </title>
    <description>
      <text lang="es" country="CO">Checking Design es un aplicativo web de autodiagnóstico en gestión de diseño y desarrollo de producto, el cual contiene diferentes herramientas que ayudan a realizar: Autodiagnóstico, definición estratégica de producto, conceptualización, pre-producción, y pre-comercialización, permitiendo identificar el estado de inserción del diseño al interior de sus organizaciones. Gracias a la aplicación de las herramientas de Checking Design, obtendrá un mapa de ruta para aumentar y mejorar el desarrollo de productos innovadores, a través de una adecuada gestión del diseño, logrando mejorar la competitividad de su organización.</text>
      </description>
    <jurisdiccion>Colombia</jurisdiccion>
    <numeroSolicitud>3. Empresarial (1366357)</numeroSolicitud>
    </patente>
  <patente id="23" type="Marca Mixta">
    <title>
      <text lang="en" country="US">Checking Design (9, 41, 42)</text>
      </title>
    <description>
      <text lang="es" country="CO">Checking Design es un aplicativo web de autodiagnóstico en gestión de diseño y desarrollo de producto, el cual contiene diferentes herramientas que ayudan a realizar: Autodiagnóstico, definición estratégica de producto, conceptualización, pre-producción, y pre-comercialización, permitiendo identificar el estado de inserción del diseño al interior de sus organizaciones. Gracias a la aplicación de las herramientas de Checking Design, obtendrá un mapa de ruta para aumentar y mejorar el desarrollo de productos innovadores, a través de una adecuada gestión del diseño, logrando mejorar la competitividad de su organización.</text>
      </description>
    <jurisdiccion>Colombia</jurisdiccion>
    <numeroSolicitud>SD2017/0024634</numeroSolicitud>
    </patente>
  <patente id="24" type="Patente - Invención">
    <title>
      <text lang="es" country="CO">Dispositivo para recubrir partes energizadas</text>
      </title>
    <description>
      <text lang="es" country="CO">Sistemas de protección física para equipos eléctricos especiales en las subestaciones eléctricas, mediante herramientas como la manufactura aditiva. Es un forro que se pone en una subestación eléctrica, tiene función econóligca para la presevnción de la muerte de la fauna pues los animales en el putumayo se acercan a las estaciones, y función técnica, para prevenir el daño de la subestación por el animal que puede queda pegado</text>
      </description>
    <jurisdiccion>Colombia</jurisdiccion>
    <numeroSolicitud>NC2021/0010900</numeroSolicitud>
    </patente>
  <patente id="25" type="Marca Mixta">
    <title>
      <text lang="ca" country="US">CONTROL VIT (9, 38, 42)</text>
      </title>
    <description>
      <text lang="es" country="CO">Apoyo remoto en tiempo real para monitorear de manera permanente a los pacientes con falla cardiaca, con el fin de detectar de manera precoz y oportuna complicaciones, por medio de un aplicativo que contiene información para mejorar el autocuidado y le permite al paciente registrar biomedidas (peso, presión arterial, frecuencia cardiaca).y síntomas de descompensación que generaran alertas al profesional de salud y, de esta manera, contribuye a mejorar la adherencia al tratamiento, calidad de vida, reducir los reingresos hospitalarios, ampliar la cobertura y la eficiencia operativa del servicio; además, sobre los datos obtenidos por el aplicativo, mejorar el control de calidad y permitir un análisis poblacional.</text>
      </description>
    <jurisdiccion>Colombia</jurisdiccion>
    <numeroSolicitud>SD2018/0081942</numeroSolicitud>
    </patente>
  <patente id="26" type="Registro de Software">
    <title>
      <text lang="no" country="US">CONTROL VIT</text>
      </title>
    <description>
      <text lang="es" country="CO">Apoyo remoto en tiempo real para monitorear de manera permanente a los pacientes con falla cardiaca, con el fin de detectar de manera precoz y oportuna complicaciones, por medio de un aplicativo que contiene información para mejorar el autocuidado y le permite al paciente registrar biomedidas (peso, presión arterial, frecuencia cardiaca).y síntomas de descompensación que generaran alertas al profesional de salud y, de esta manera, contribuye a mejorar la adherencia al tratamiento, calidad de vida, reducir los reingresos hospitalarios, ampliar la cobertura y la eficiencia operativa del servicio; además, sobre los datos obtenidos por el aplicativo, mejorar el control de calidad y permitir un análisis poblacional.</text>
      </description>
    <jurisdiccion>Colombia</jurisdiccion>
    <numeroSolicitud>138180</numeroSolicitud>
    </patente>
  <patente id="27" type="Registro de Software">
    <title>
      <text lang="en" country="US">ADHERENCIA DE TRATAMIENTO
FARMACOLOGICO</text>
      </title>
    <description>
      <text lang="es" country="CO">Apoyo remoto en tiempo real para monitorear de manera permanente a los pacientes con falla cardiaca, con el fin de detectar de manera precoz y oportuna complicaciones, por medio de un aplicativo que contiene información para mejorar el autocuidado y le permite al paciente registrar biomedidas (peso, presión arterial, frecuencia cardiaca).y síntomas de descompensación que generaran alertas al profesional de salud y, de esta manera, contribuye a mejorar la adherencia al tratamiento, calidad de vida, reducir los reingresos hospitalarios, ampliar la cobertura y la eficiencia operativa del servicio; además, sobre los datos obtenidos por el aplicativo, mejorar el control de calidad y permitir un análisis poblacional.</text>
      </description>
    <jurisdiccion>Colombia</jurisdiccion>
    <numeroSolicitud>1345391</numeroSolicitud>
    </patente>
  <patente id="28" type="Patente - Invención">
    <title>
      <text lang="de" country="US">SISTEMA PREDICTIVO PARA APOYAR EL DIAGNÓSTICO TEMPRANODE ALTERACIONES BIOMECÁNICAS DEL PIE EN PACIENTESDIABÉTICOS</text>
      </title>
    <description>
      <text lang="es" country="CO">Plataforma de telemedicina que permite asistir al especialista en el diagnóstico, tratamiento y seguimiento continuo del pie diabético, se derivan de esta plataforma plantillas personalizadas que reduce los picos de presión en un 77%.</text>
      </description>
    <jurisdiccion>Colombia</jurisdiccion>
    <numeroSolicitud>NC2021/0015248</numeroSolicitud>
    </patente>
  <patente id="29" type="Marca Nominativa">
    <title>
      <text lang="de" country="US">DIAPETICS (42)</text>
      </title>
    <description>
      <text lang="es" country="CO">Plataforma de telemedicina que permite asistir al especialista en el diagnóstico, tratamiento y seguimiento continuo del pie diabético, se derivan de esta plataforma plantillas personalizadas que reduce los picos de presión en un 77%.</text>
      </description>
    <jurisdiccion>Colombia</jurisdiccion>
    <numeroSolicitud>16070515</numeroSolicitud>
    </patente>
  <patente id="30" type="Registro de Software">
    <title>
      <text lang="de" country="US">DISEARCH: SOFTWARE PARA LA BUSQUEDA PRIORIZADA DE HISTORIAS CLINICAS ELECTRONICAS</text>
      </title>
    <description>
      <text lang="es" country="CO">DISEARCH     es     una     herramienta     de     búsqueda    y    priorización    de    Historias    Clínicas    Electrónicas    (HCE).    Ha    sido    desarrollada  para  la  búsqueda  de  datos  estructurados    y    no    estructurados    y    produce  una  lista  priorizada  de  registros  de    pacientes    que    coinciden    con    los    criterios de búsqueda dados. En este momento se ha trabajado con el HUSI para prevalencia de enfermedades, seguimiento de pacientes.. y con esta información planterar proyectos de investigación</text>
      </description>
    <jurisdiccion>Colombia</jurisdiccion>
    <numeroSolicitud>1341426</numeroSolicitud>
    </patente>
  <patente id="31" type="Marca Mixta">
    <title>
      <text lang="de" country="US">DISEARCH (9, 42)</text>
      </title>
    <description>
      <text lang="es" country="CO">DISEARCH     es     una     herramienta     de     búsqueda    y    priorización    de    Historias    Clínicas    Electrónicas    (HCE).    Ha    sido    desarrollada  para  la  búsqueda  de  datos  estructurados    y    no    estructurados    y    produce  una  lista  priorizada  de  registros  de    pacientes    que    coinciden    con    los    criterios de búsqueda dados. En este momento se ha trabajado con el HUSI para prevalencia de enfermedades, seguimiento de pacientes.. y con esta información planterar proyectos de investigaciónpriorización de historias clinicas electrónicas</text>
      </description>
    <jurisdiccion>Colombia</jurisdiccion>
    <numeroSolicitud>15246120</numeroSolicitud>
    </patente>
  <patente id="32" type="Registro de Software">
    <title>
      <text lang="es" country="CO">EXEMED</text>
      </title>
    <description>
      <text lang="es" country="CO">Herramienta informática para el análisis de indicadores de adherencia a las guías de práctica clínica intrahospitalaria de los pacientes tratados con enfermedades crónicas.</text>
      </description>
    <jurisdiccion>Colombia</jurisdiccion>
    <numeroSolicitud>1361332</numeroSolicitud>
    </patente>
  <patente id="33" type="Patente - Invención">
    <title>
      <text lang="es" country="CO">Dispositivo Intraoral para el Tratamiento de Apnea del Sueño y Ronquido</text>
      </title>
    <description>
      <text lang="es" country="CO">DUBSA®: Dispositivo intraoral de avance mandibular para facilitar la respiración en pacientes con AOS. Este cuenta con un mecanismo gradual y autoajustable, haciéndolo totalmente adaptable, cómodo y que permite un avance de la mandíbula, de la lengua, y movimientos mandibulares de lateralidad, facilitando el paso del aire, aumentando su eficacia con respecto a los otros dispositivos en el tratamiento de la AOS y ronquido.</text>
      </description>
    <jurisdiccion>Colombia</jurisdiccion>
    <numeroSolicitud>NC2016/0001239</numeroSolicitud>
    </patente>
  <patente id="34" type="Marca Mixta">
    <title>
      <text lang="af" country="US">DUBSA (9, 10, 41, 42, 44)</text>
      </title>
    <description>
      <text lang="es" country="CO">DUBSA®: Dispositivo intraoral de avance mandibular para facilitar la respiración en pacientes con AOS. Este cuenta con un mecanismo gradual y autoajustable, haciéndolo totalmente adaptable, cómodo y que permite un avance de la mandíbula, de la lengua, y movimientos mandibulares de lateralidad, facilitando el paso del aire, aumentando su eficacia con respecto a los otros dispositivos en el tratamiento de la AOS y ronquido.</text>
      </description>
    <jurisdiccion>Colombia</jurisdiccion>
    <numeroSolicitud>	SD2019/0038037</numeroSolicitud>
    </patente>
  <patente id="36" type="Patente - Invención">
    <title>
      <text lang="es" country="CO">Estructura modular transportable de elementos prefabricados para la construcción de edificaciones</text>
      </title>
    <description>
      <text lang="es" country="CO">Estructura modular transportable de elementos prefabricados para la construcción de edificaciones. La estructura modular es fabricada con tetrapak, el cual tiene cartón  en su mayoria y otros compuestos</text>
      </description>
    <jurisdiccion>Colombia</jurisdiccion>
    <numeroSolicitud>NC2019/0012797</numeroSolicitud>
    </patente>
  <patente id="40" type="Patente - Invención">
    <title>
      <text lang="es" country="CO">Herramienta ergonómica para el corte de flores y frutos. Modelo I</text>
      </title>
    <description>
      <text lang="es" country="CO">Herramienta ergonómica para el corte de flores y frutos.</text>
      </description>
    <jurisdiccion>Colombia</jurisdiccion>
    <numeroSolicitud>10-093246</numeroSolicitud>
    </patente>
  <patente id="44" type="Patente - Invención">
    <title>
      <text lang="es" country="CO">Herramienta ergonómica para el corte de flores y frutos. Modelo II</text>
      </title>
    <description>
      <text lang="es" country="CO">Herramienta ergonómica para el corte de flores y frutos.</text>
      </description>
    <jurisdiccion>Colombia</jurisdiccion>
    <numeroSolicitud>10-093249</numeroSolicitud>
    </patente>
  <patente id="46" type="Patente - Invención">
    <title>
      <text lang="es" country="CO">Fracción Bioactiva de Achyrocline Bogotensis (Kunth) Dc. (Compositae) con Actividad Antiviral</text>
      </title>
    <description>
      <text lang="es" country="CO">Fracción bioactiva (extracto) de achyrocline bogotensis (planta medicinal) que se da en la zona del centro del país, con actividad antiviral para tratamiento Enfermedad Diarreica Aguda. La idea del extracto es que no ataca el virus si no que es un suplemento</text>
      </description>
    <jurisdiccion>Colombia</jurisdiccion>
    <numeroSolicitud>16017515</numeroSolicitud>
    </patente>
  <patente id="47" type="Patente - Invención">
    <title>
      <text lang="es" country="CO">Guia lineal de rodillos compacta</text>
      </title>
    <description>
      <text lang="es" country="CO">Guia lineal de rodillos compacta</text>
      </description>
    <jurisdiccion>Estados Unidos</jurisdiccion>
    <numeroSolicitud>US 14363156</numeroSolicitud>
    </patente>
  <patente id="50" type="Patente - Invención">
    <title>
      <text lang="en" country="US">System and Method for an Universal Head-Up Display with Multiple Interaction Methods</text>
      </title>
    <description>
      <text lang="es" country="CO">Sistema y método de interacción con un dispositivo móvil utilizando un visualizador head-up. Es un sistema (es un hardware en una pantalla) que permite visualizar las condiciones de los vehículos como por ejemplo si tiene bien la temperatura del motor, y además interactura con aplicaciones como waze, radio. Tiene tambien tiene un hardware que es un anillo que se coloca en las manos para manipular el head up y que se conecta con el celular a traves de una app.</text>
      </description>
    <jurisdiccion>Estados Unidos</jurisdiccion>
    <numeroSolicitud>62607913</numeroSolicitud>
    </patente>
  <patente id="51" type="Patente - Invención">
    <title>
      <text lang="es" country="CO">Sistema y Método de Interacción con un Dispositivo Móvil
Utilizando un Visualizador Head-up</text>
      </title>
    <description>
      <text lang="es" country="CO">Sistema y método de interacción con un dispositivo móvil utilizando un visualizador head-up. Es un sistema (es un hardware en una pantalla) que permite visualizar las condiciones de los vehículos como por ejemplo si tiene bien la temperatura del motor, y además interactura con aplicaciones como waze, radio. Tiene tambien tiene un hardware que es un anillo que se coloca en las manos para manipular el head up y que se conecta con el celular a traves de una app.</text>
      </description>
    <jurisdiccion>PCT</jurisdiccion>
    <numeroSolicitud>PCT/IB2018/060360</numeroSolicitud>
    </patente>
  <patente id="52" type="Patente - Invención">
    <title>
      <text lang="en" country="US">System and method for interacting with a mobile device using a head-up display</text>
      </title>
    <description>
      <text lang="es" country="CO">Sistema y método de interacción con un dispositivo móvil utilizando un visualizador head-up. Es un sistema (es un hardware en una pantalla) que permite visualizar las condiciones de los vehículos como por ejemplo si tiene bien la temperatura del motor, y además interactura con aplicaciones como waze, radio. Tiene tambien tiene un hardware que es un anillo que se coloca en las manos para manipular el head up y que se conecta con el celular a traves de una app.</text>
      </description>
    <jurisdiccion>Estados Unidos</jurisdiccion>
    <numeroSolicitud>16/954,975 US2020310552A1</numeroSolicitud>
    </patente>
  <patente id="53" type="Patente - Invención">
    <title>
      <text lang="es" country="CO">Sistema y método de interacción con un dispositivo móvil utilizando un visualizador head-up</text>
      </title>
    <description>
      <text lang="es" country="CO">Sistema y método de interacción con un dispositivo móvil utilizando un visualizador head-up. Es un sistema (es un hardware en una pantalla) que permite visualizar las condiciones de los vehículos como por ejemplo si tiene bien la temperatura del motor, y además interactura con aplicaciones como waze, radio. Tiene tambien tiene un hardware que es un anillo que se coloca en las manos para manipular el head up y que se conecta con el celular a traves de una app.</text>
      </description>
    <jurisdiccion>Colombia</jurisdiccion>
    <numeroSolicitud>NC2020/0008359</numeroSolicitud>
    </patente>
  <patente id="54" type="Patente - Invención">
    <title>
      <text lang="en" country="US">Method for Manufacturing a Thin Film Consisting of a Colloidal Crystal Infiltrated with the Luminescent MDMO-PPV Polymer Made of Silica (SIO2) Spheres, Having a Face-Centered Cubic System(FCC)</text>
      </title>
    <description>
      <text lang="es" country="CO">La tecnología Lumière consiste en el desarrollo de un método de fabricación rápido, sencillo y reproducible, de diodos emisores de luz orgánicos OLED, que incorpora a la región activa de los mismos, una película construida a partir de nano partículas de dióxido de silicio (SiO ), las cuales son infiltradas con un polímero luminiscente que se dispone en un arreglo altamente simétrico. Este método de fabricación, mejora la eficiencia energética de los OLED producidos en un 30% frente a los OLED tradicionales. La película luminiscente obtenida, puede ser acoplada fácilmente a los procesos usuales de manufactura de los OLED</text>
      </description>
    <jurisdiccion>Estados Unidos</jurisdiccion>
    <numeroSolicitud>15/117,313</numeroSolicitud>
    </patente>
  <patente id="55" type="Patente - Invención">
    <title>
      <text lang="es" country="CO">Enzima Esterasa Modificada Enantioselectiva y proceso para la Obtención de la Misma</text>
      </title>
    <description>
      <text lang="es" country="CO">Lipasas estable, aislada de un microorganismo extremófilo, que realiza síntesis de esteres útiles en la producción de aromas y sabores en la industria alimenticia, cosmética, farmacéutica y de productos de aseo (detergentes) y cuidado personal. Este biocatalizador tienen una alta demanda en la transformación de grasas derivadas del aceite de palma para la obtención de microcomponentes con alto valor agregado como esteroles, vitamina A y E, fosfolípidos y ácidos grasos. Adicionalmente, las lipasas permiten la generación de una amplia gama de moléculas que reemplazan el uso de compuestos sintéticos en los procesos productivos.</text>
      </description>
    <jurisdiccion>Colombia</jurisdiccion>
    <numeroSolicitud>14093195</numeroSolicitud>
    </patente>
  <patente id="57" type="Patente - Invención">
    <title>
      <text lang="es" country="CO">Método de Detección de Líneas de Transmisión de Energía en Tiempo Real con Vehículos Aéreos No Tripulados</text>
      </title>
    <description>
      <text lang="es" country="CO">Método de detección de líneas de transmisión de energía en tiempo real con vehículos aéreo no tripulados. 

Es una metodología que permite detectar fallas en las líneas eléctricas o en los oleoductos. Es un dfron que utónomamente vuela sobre las líneas eléctricas y toma videos. No es necesario que alguien esté manejando el dron. Esto permite monitorear a largas distancias</text>
      </description>
    <jurisdiccion>Colombia</jurisdiccion>
    <numeroSolicitud>NC2018/0013805</numeroSolicitud>
    </patente>
  <patente id="59" type="Patente - Invención">
    <title>
      <text lang="es" country="CO">Método para la Fabricación de una Película Delgada Formada por un Cristal Coloidal Infiltrado con un Polímero Luminiscente MDMOPPV</text>
      </title>
    <description>
      <text lang="es" country="CO">La tecnología Lumière consiste en el desarrollo de un método de fabricación rápido, sencillo y reproducible, de diodos emisores de luz orgánicos OLED, que incorpora a la región activa de los mismos, una película construida a partir de nano partículas de dióxido de silicio (SiO ), las cuales son infiltradas con un polímero luminiscente que se dispone en un arreglo altamente simétrico. Este método de fabricación, mejora la eficiencia energética de los OLED producidos en un 30% frente a los OLED tradicionales. La película luminiscente obtenida, puede ser acoplada fácilmente a los procesos usuales de manufactura de los OLED</text>
      </description>
    <jurisdiccion>Colombia</jurisdiccion>
    <numeroSolicitud>14025971</numeroSolicitud>
    </patente>
  <patente id="61" type="Patente - Invención">
    <title>
      <text lang="es" country="CO">Proceso para la Obtención de un Biomaterial Aglomerado Enriquecido para Siembra en Vivero</text>
      </title>
    <description>
      <text lang="es" country="CO">Sustrato de siembra en vivero fabricado a partir de residuos de la industria maderera, enriquecido con fertilizantes (promofort) y microorganismos promotores de crecimiento vegetal. La planta posteriormente es plantada en tierra para contoinuar su desarrollo</text>
      </description>
    <jurisdiccion>Colombia</jurisdiccion>
    <numeroSolicitud>NC2022/0001320</numeroSolicitud>
    </patente>
  <patente id="62" type="Patente - Invención">
    <title>
      <text lang="es" country="CO">Método para producir selectivamente metabolitos a partir de una microalga</text>
      </title>
    <description>
      <text lang="es" country="CO">Proceso de manipulación del crecimiento de la microalga Galdieria sp. USBA-GBX 832 para la obtención de un extracto con cantidades interesantes de metabolitos de moléculas complejas, acumulados en la biomasa que poseen capacidades antioxidantes, como también antiangiogénica, citotóxica, anticancerígena, antiobesidad y antimicrobiana.</text>
      </description>
    <jurisdiccion>Colombia</jurisdiccion>
    <numeroSolicitud>NC2020/0003916</numeroSolicitud>
    </patente>
  <patente id="63" type="Patente - Invención">
    <title>
      <text lang="es" country="CO">Método para producir selectivamente metabolitos a partir de microalgas del género galdieria</text>
      </title>
    <description>
      <text lang="es" country="CO">Proceso de manipulación del crecimiento de la microalga Galdieria sp. USBA-GBX 832 para la obtención de un extracto con cantidades interesantes de metabolitos de moléculas complejas, acumulados en la biomasa que poseen capacidades antioxidantes, como también antiangiogénica, citotóxica, anticancerígena, antiobesidad y antimicrobiana.</text>
      </description>
    <jurisdiccion>Colombia</jurisdiccion>
    <numeroSolicitud>NC2020/0009174</numeroSolicitud>
    </patente>
  <patente id="65" type="Patente - Invención">
    <title>
      <text lang="en" country="US">COMPOSICIÓN FARMACÉUTICA QUE COMPRENDE DERIVADOS DEL ÁCIDO GÁLICO
Y 3,4,5,6-TETRAKIS[(3,4,5-TRIHIDROXIBENZOIL)OXI]OXAN-2-IL]METIL-3,4,5-TRIHIDROXI BENZOATO "</text>
      </title>
    <description>
      <text lang="es" country="CO">Phairilab es un conjunto de invenciones desarrolladas a partir de las propiedades funcionales de las plantas DIvidivi y Anamú que tienen características especiales para desarrollar productos dermocosméticos, suplementos alimenticios  y fitomedicamentos para el tratamiento de pacientes con cancer.</text>
      </description>
    <jurisdiccion>Colombia</jurisdiccion>
    <numeroSolicitud>12-236193</numeroSolicitud>
    </patente>
  <patente id="66" type="Patente - Invención">
    <title>
      <text lang="en" country="US">Consortium of Fungi Immobilized on a Laminar Lignocellulose Carrier for the Treatment of Wastewater and Method for Producing Same</text>
      </title>
    <description>
      <text lang="es" country="CO">Consorcio de hongos inmovilizados sobre un portador laminar de lignocelulosa para el tratamiento de aguas residuales y proceso para la elaboración del mismo</text>
      </description>
    <jurisdiccion>Estados Unidos</jurisdiccion>
    <numeroSolicitud>US 15/103,712</numeroSolicitud>
    </patente>
  <patente id="69" type="Marca Mixta">
    <title>
      <text lang="id" country="US">Phairi Lab (5, 42, 44)</text>
      </title>
    <description>
      <text lang="es" country="CO">Phairilab es un conjunto de invenciones desarrolladas a partir de las propiedades funcionales de las plantas DIvidivi y Anamú que tienen características especiales para desarrollar productos dermocosméticos, suplementos alimenticios  y fitomedicamentos para el tratamiento de pacientes con cancer.</text>
      </description>
    <jurisdiccion>Colombia</jurisdiccion>
    <numeroSolicitud>12164206</numeroSolicitud>
    </patente>
  <patente id="70" type="Lema Comercial">
    <title>
      <text lang="es" country="CO">En Equilibrio con la Naturaleza</text>
      </title>
    <description>
      <text lang="es" country="CO">Phairilab es un conjunto de invenciones desarrolladas a partir de las propiedades funcionales de las plantas DIvidivi y Anamú que tienen características especiales para desarrollar productos dermocosméticos, suplementos alimenticios  y fitomedicamentos para el tratamiento de pacientes con cancer.</text>
      </description>
    <jurisdiccion>Colombia</jurisdiccion>
    <numeroSolicitud>12165485</numeroSolicitud>
    </patente>
  <patente id="71" type="Patente - PCT">
    <title>
      <text lang="es" country="CO">Fracción bioactiva de Petiveria alliacea, composición farmacéutica que la contiene y combinación con agentes inmunoestimulantes para el tratamiento del cáncer</text>
      </title>
    <description>
      <text lang="es" country="CO">Phairilab es un conjunto de invenciones desarrolladas a partir de las propiedades funcionales de las plantas DIvidivi y Anamú que tienen características especiales para desarrollar productos dermocosméticos, suplementos alimenticios  y fitomedicamentos para el tratamiento de pacientes con cancer.</text>
      </description>
    <jurisdiccion>PCT</jurisdiccion>
    <numeroSolicitud>PCT/IB2010/002504 (22/09/2010) WO/2011/039629 (07/04/2011)</numeroSolicitud>
    </patente>
  <patente id="72" type="NO APLICA">
    <title>
      <text lang="pt" country="US">NO APLICA</text>
      </title>
    <description>
      <text lang="es" country="CO">Alimento a base de harina de yuca y otros tubérculos como suplemento alimenticio para personas con errores innatos del metabolismo, como estas personas tienen deficiencias en el organismo deben tener una dieta específica rica en ciertos compuestos.</text>
      </description>
    <jurisdiccion>NO APLICA</jurisdiccion>
    <numeroSolicitud>NO APLICA</numeroSolicitud>
    </patente>
  <patente id="74" type="Patente - PCT">
    <title>
      <text lang="es" country="CO">Inoculante Biológico para Promoción de Crecimiento de las Especies Forestales y método para su Obtención</text>
      </title>
    <description>
      <text lang="es" country="CO">bioinoculante líquido promotor de crecimiento vegetal,que presenta diferentes actividades biológicas que incluyen la producción de ácidos orgánicos, de sideróforos, de la enzima nitrogenasa y de reguladores de crecimiento vegetal, que aplicado en la fase inicial del cultivo obtiene resultados positivos tales como un mejor rendimiento comparado con el obtenido al aplicar otros productos similares.</text>
      </description>
    <jurisdiccion>PCT</jurisdiccion>
    <numeroSolicitud>PCT/IB2014/000527</numeroSolicitud>
    </patente>
  <patente id="76" type="Patente - Invención">
    <title>
      <text lang="es" country="CO">Proceso de Inmovilización de Bacterias Gram Negativas para Estimular el Crecimiento Vegetal</text>
      </title>
    <description>
      <text lang="es" country="CO">bioinoculante líquido promotor de crecimiento vegetal,que presenta diferentes actividades biológicas que incluyen la producción de ácidos orgánicos, de sideróforos, de la enzima nitrogenasa y de reguladores de crecimiento vegetal, que aplicado en la fase inicial del cultivo obtiene resultados positivos tales como un mejor rendimiento comparado con el obtenido al aplicar otros productos similares.</text>
      </description>
    <jurisdiccion>Colombia</jurisdiccion>
    <numeroSolicitud>13094384</numeroSolicitud>
    </patente>
  <patente id="77" type="Patente - Invención">
    <title>
      <text lang="es" country="CO">Sistema que Conforma una Estación de Espectroscopias Ópticas</text>
      </title>
    <description>
      <text lang="es" country="CO">Integral Spectrum consiste en un equipo modular que ensambla una estación de 5 tipos de espectroscopias (absorbancia, transmitancia, reectancia, fotoluminiscencia y Raman) para el estudio de las propiedades ópticas de diferentes materiales en cualquiera de los estados (sólido, líquido, gas, plasma o película delgada) .La tecnología presenta excelentes características de sensibilidad y trazabilidad gracias al uso de técnicas de ampliación que mejoran la transmisión de señal. La óptica permite enfocar el haz de luz en un punto específico de la muestra (1mm), mejorando la precisión de los resultados. Por último, el diseño del equipo permite adaptarse a las necesidades específicas del usuario, brindado gran precisión de los resultados y la personalización de la estación.</text>
      </description>
    <jurisdiccion>Colombia</jurisdiccion>
    <numeroSolicitud>NC2016/0000550</numeroSolicitud>
    </patente>
  <patente id="78" type="Registro de Software">
    <title>
      <text lang="ro" country="US">Integral Spectrum</text>
      </title>
    <description>
      <text lang="es" country="CO">Integral Spectrum consiste en un equipo modular que ensambla una estación de 5 tipos de espectroscopias (absorbancia, transmitancia, re?ectancia, fotoluminiscencia y Raman) para el estudio de las propiedades ópticas de diferentes materiales en cualquiera de los estados (sólido, líquido, gas, plasma o película delgada) .La tecnología presenta excelentes características de sensibilidad y trazabilidad gracias al uso de técnicas de ampliación que mejoran la transmisión de señal. La óptica permite enfocar el haz de luz en un punto específico de la muestra (1mm), mejorando la precisión de los resultados. Por último, el diseño del equipo permite adaptarse a las necesidades específicas del usuario, brindado gran precisión de los resultados y la personalización de la estación.</text>
      </description>
    <jurisdiccion>Colombia</jurisdiccion>
    <numeroSolicitud>1389406</numeroSolicitud>
    </patente>
  <patente id="79" type="Marca Mixta">
    <title>
      <text lang="hu" country="US">BIOALLPA (1, 42)</text>
      </title>
    <description>
      <text lang="es" country="CO">bioinoculante líquido promotor de crecimiento vegetal,que presenta diferentes actividades biológicas que incluyen la producción de ácidos orgánicos, de sideróforos, de la enzima nitrogenasa y de reguladores de crecimiento vegetal, que aplicado en la fase inicial del cultivo obtiene resultados positivos tales como un mejor rendimiento comparado con el obtenido al aplicar otros productos similares.</text>
      </description>
    <jurisdiccion>Colombia</jurisdiccion>
    <numeroSolicitud>12173180</numeroSolicitud>
    </patente>
  <patente id="80" type="Marca Nominativa">
    <title>
      <text lang="id" country="US">PROMOFORT (1)</text>
      </title>
    <description>
      <text lang="es" country="CO">bioinoculante líquido promotor de crecimiento vegetal,que presenta diferentes actividades biológicas que incluyen la producción de ácidos orgánicos, de sideróforos, de la enzima nitrogenasa y de reguladores de crecimiento vegetal, que aplicado en la fase inicial del cultivo obtiene resultados positivos tales como un mejor rendimiento comparado con el obtenido al aplicar otros productos similares.</text>
      </description>
    <jurisdiccion>Colombia</jurisdiccion>
    <numeroSolicitud>16103183</numeroSolicitud>
    </patente>
  <patente id="81" type="Patente - Invención">
    <title>
      <text lang="en" country="US">Enantioselective Modified Esterase Enzyme and Method for the Production Thereof</text>
      </title>
    <description>
      <text lang="es" country="CO">Lipasas estable, aislada de un microorganismo extremófilo, que realiza síntesis de esteres útiles en la producción de aromas y sabores en la industria alimenticia, cosmética, farmacéutica y de productos de aseo (detergentes) y cuidado personal. Este biocatalizador tienen una alta demanda en la transformación de grasas derivadas del aceite de palma para la obtención de microcomponentes con alto valor agregado como esteroles, vitamina A y E, fosfolípidos y ácidos grasos. Adicionalmente, las lipasas permiten la generación de una amplia gama de moléculas que reemplazan el uso de compuestos sintéticos en los procesos productivos.</text>
      </description>
    <jurisdiccion>Estados Unidos</jurisdiccion>
    <numeroSolicitud>No. Patente: 10,400,224 Solicitud: 15/307,254</numeroSolicitud>
    </patente>
  <patente id="82" type="Patente - PCT">
    <title>
      <text lang="en" country="US">BIOINOCULANT COMPOSITION</text>
      </title>
    <description>
      <text lang="es" country="CO">bioinoculante líquido promotor de crecimiento vegetal,que presenta diferentes actividades biológicas que incluyen la producción de ácidos orgánicos, de sideróforos, de la enzima nitrogenasa y de reguladores de crecimiento vegetal, que aplicado en la fase inicial del cultivo obtiene resultados positivos tales como un mejor rendimiento comparado con el obtenido al aplicar otros productos similares.</text>
      </description>
    <jurisdiccion>PCT</jurisdiccion>
    <numeroSolicitud>PCT/IB2020/052027</numeroSolicitud>
    </patente>
  <patente id="84" type="Marca Mixta">
    <title>
      <text lang="vi" country="US">QUEMES (7, 9, 41, 42)</text>
      </title>
    <description>
      <text lang="es" country="CO">Metodología de formación integral de jóvenes para generar las habilidades tecnológicas del siglo XXI usando robots como herramienta para la solución de problemas cotidianos. Teatro robótico</text>
      </description>
    <jurisdiccion>Colombia</jurisdiccion>
    <numeroSolicitud>SD2016/0057980</numeroSolicitud>
    </patente>
  <patente id="85" type="Registro de Software">
    <title>
      <text lang="es" country="CO">Quemes educación tecnológica soportada en robótica educativa</text>
      </title>
    <description>
      <text lang="es" country="CO">Metodología de formación integral de jóvenes para generar las habilidades tecnológicas del siglo XXI usando robots como herramienta para la solución de problemas cotidianos. Teatro robótico</text>
      </description>
    <jurisdiccion>Colombia</jurisdiccion>
    <numeroSolicitud>13-72-412</numeroSolicitud>
    </patente>
  <patente id="86" type="Patente - Invención">
    <title>
      <text lang="es" country="CO">Dispositivo para inspección y reparación de tuberias</text>
      </title>
    <description>
      <text lang="es" country="CO">Dispositivo para inspección y reparación de tuberías hidrosanitarias operado remotamente.Este dispositivo es un robot que se maneja de manera inhalámbrica, se pilotea con con un control</text>
      </description>
    <jurisdiccion>Colombia</jurisdiccion>
    <numeroSolicitud>NC2019/0009551</numeroSolicitud>
    </patente>
  <patente id="87" type="Patente - Invención">
    <title>
      <text lang="en" country="US">Method for Modeling and Executing Complex Systems based on Concurrent BDI Architecture with Hybrid Hardware/Software Agents</text>
      </title>
    <description>
      <text lang="es" country="CO">Sistema que controla un robot que responda a imprevistos en un ambiente complejo, tobot de compañia para ancianos. Los robot deben sortear obstaculos mientras interactuan con los humanos</text>
      </description>
    <jurisdiccion>Estados Unidos</jurisdiccion>
    <numeroSolicitud>US16/652,610</numeroSolicitud>
    </patente>
  <patente id="89" type="Patente - Invención">
    <title>
      <text lang="es" country="CO">Método y sistema de apoyo en la ejecución de actividades para usuarios con déficit cognitivo</text>
      </title>
    <description>
      <text lang="es" country="CO">Sistema de apoyo para pacientes con demencia fronto temporal, los cuales pierden la conciencia del orden de ejecución de una actividad. Se trata de unos dispositivos que cuentan con alarmas lumínicas y de sonido para indicar al paciente el orden y secuencia de las actividades a realizar.</text>
      </description>
    <jurisdiccion>Colombia</jurisdiccion>
    <numeroSolicitud>NC2021/0015195</numeroSolicitud>
    </patente>
  <patente id="90" type="Patente - Invención">
    <title>
      <text lang="es" country="CO">Mecanotransductor para la estimulación de cultivos celulares</text>
      </title>
    <description>
      <text lang="es" country="CO">La presente invención se relaciona con un aparato mecatrónico para llevar a cabo la estimulación mecánica de cultivos celulares in Vitro, el cual transmite diferentes intensidades de fuerza a la células adheridas a la superficie en frascos de cultivo, con el fin de estudiar y analizar las diferentes fases del ciclo celular. La estimulación mecánica se basa en la producción de deformaciones cíclicas de diferentes magnitudes y frecuencias en los frascos de cultivo, dando la posibilidad de regular los tiempos de estimulo y reposo mediante un sistema de control automatizado que permite programar el número de ciclos a realizar en un tiempo establecido por el usuario, donde el aparato mecatrónico es controlado por medio de un sistema de control encargado de recibir la información por parte del usuario con relación con los intervalos de tiempo en los cuales se desea hacer la estimulación mecánica en cada uno de los frascos de cultivo y de enviar las diferentes señales al servomotor, que realiza giros para transmitir el movimiento a un eje de levas que produce la estimulación mecánica a los frascos de cultivo.</text>
      </description>
    <jurisdiccion>Colombia</jurisdiccion>
    <numeroSolicitud>10-164988</numeroSolicitud>
    </patente>
  <patente id="93" type="Patente - Invención">
    <title>
      <text lang="en" country="US">Bioactive fraction of petiveria alliacea, Pharmaceutical composition containing same, and combination with immunostimulants for treating cancer</text>
      </title>
    <description>
      <text lang="es" country="CO">Phairilab es un conjunto de invenciones desarrolladas a partir de las propiedades funcionales de las plantas DIvidivi y Anamú que tienen características especiales para desarrollar productos dermocosméticos, suplementos alimenticios  y fitomedicamentos para el tratamiento de pacientes con cancer.</text>
      </description>
    <jurisdiccion>Estados Unidos</jurisdiccion>
    <numeroSolicitud>13/499,798</numeroSolicitud>
    </patente>
  <patente id="94" type="Patente - Invención">
    <title>
      <text lang="en" country="US">Biological inoculant for promoting the growth of forest species and method for producing same</text>
      </title>
    <description>
      <text lang="es" country="CO">bioinoculante líquido promotor de crecimiento vegetal,que presenta diferentes actividades biológicas que incluyen la producción de ácidos orgánicos, de sideróforos, de la enzima nitrogenasa y de reguladores de crecimiento vegetal, que aplicado en la fase inicial del cultivo obtiene resultados positivos tales como un mejor rendimiento comparado con el obtenido al aplicar otros productos similares.</text>
      </description>
    <jurisdiccion>Estados Unidos</jurisdiccion>
    <numeroSolicitud>14/783,393</numeroSolicitud>
    </patente>
  <patente id="98" type="Patente - Invención">
    <title>
      <text lang="es" country="CO">Método de priorización de historias clínicas electrónicas para estudios retrospectivos</text>
      </title>
    <description>
      <text lang="es" country="CO">DISEARCH     es     una     herramienta     de     búsqueda    y    priorización    de    Historias    Clínicas    Electrónicas    (HCE).    Ha    sido    desarrollada  para  la  búsqueda  de  datos  estructurados    y    no    estructurados    y    produce  una  lista  priorizada  de  registros  de    pacientes    que    coinciden    con    los    criterios de búsqueda dados. En este momento se ha trabajado con el HUSI para prevalencia de enfermedades, seguimiento de pacientes.. y con esta información planterar proyectos de investigaciónpriorización de historias clinicas electrónicas</text>
      </description>
    <jurisdiccion>Colombia</jurisdiccion>
    <numeroSolicitud>14- 75996</numeroSolicitud>
    </patente>
  <patente id="100" type="Patente - Invención">
    <title>
      <text lang="es" country="CO">Medio de cultivo para la producción de ácidos orgánicos fermantativos</text>
      </title>
    <description>
      <text lang="es" country="CO">MEDIO DE CULTIVO PARA LA PRODUCCIÓN DE ÁCIDOS ORGÁNICOS FERMENTATIVOS</text>
      </description>
    <jurisdiccion>Colombia</jurisdiccion>
    <numeroSolicitud>15/251084</numeroSolicitud>
    </patente>
  <patente id="101" type="Patente - Invención">
    <title>
      <text lang="fr" country="US">Bioinoculant Composition</text>
      </title>
    <description>
      <text lang="es" country="CO">bioinoculante líquido promotor de crecimiento vegetal,que presenta diferentes actividades biológicas que incluyen la producción de ácidos orgánicos, de sideróforos, de la enzima nitrogenasa y de reguladores de crecimiento vegetal, que aplicado en la fase inicial del cultivo obtiene resultados positivos tales como un mejor rendimiento comparado con el obtenido al aplicar otros productos similares.</text>
      </description>
    <jurisdiccion>Estados Unidos</jurisdiccion>
    <numeroSolicitud>16/296,786</numeroSolicitud>
    </patente>
  <patente id="103" type="Patente - Invención">
    <title>
      <text lang="pt" country="US">Processo de imobilização para obter um inoculante biológico estimulador do crescimento vegetal, suporte de teca, e, inoculante biológico estimulador de crescimiento</text>
      </title>
    <description>
      <text lang="es" country="CO">bioinoculante líquido promotor de crecimiento vegetal,que presenta diferentes actividades biológicas que incluyen la producción de ácidos orgánicos, de sideróforos, de la enzima nitrogenasa y de reguladores de crecimiento vegetal, que aplicado en la fase inicial del cultivo obtiene resultados positivos tales como un mejor rendimiento comparado con el obtenido al aplicar otros productos similares.</text>
      </description>
    <jurisdiccion>Brasil</jurisdiccion>
    <numeroSolicitud>BR 11 2015 025912 0</numeroSolicitud>
    </patente>
  <patente id="104" type="Patente - Invención">
    <title>
      <text lang="en" country="US">Novel biofertilizer based on a bacterial consortium of four strains isolated from roots of tree Tectona grandis</text>
      </title>
    <description>
      <text lang="es" country="CO">bioinoculante líquido promotor de crecimiento vegetal,que presenta diferentes actividades biológicas que incluyen la producción de ácidos orgánicos, de sideróforos, de la enzima nitrogenasa y de reguladores de crecimiento vegetal, que aplicado en la fase inicial del cultivo obtiene resultados positivos tales como un mejor rendimiento comparado con el obtenido al aplicar otros productos similares.</text>
      </description>
    <jurisdiccion>Estados Unidos</jurisdiccion>
    <numeroSolicitud>62572562</numeroSolicitud>
    </patente>
  <patente id="105" type="Patente - PCT">
    <title>
      <text lang="en" country="US">Real - Time Multi - Agent BDI Architecture with Agent Migration and Methods Thereof</text>
      </title>
    <description>
      <text lang="es" country="CO">Sistema que controla un robot que responda a imprevistos en un ambiente complejo, tobot de compañia para ancianos. Los robot deben sortear obstaculos mientras interactuan con los humanos</text>
      </description>
    <jurisdiccion>PCT</jurisdiccion>
    <numeroSolicitud>PCT/IB2018/057615</numeroSolicitud>
    </patente>
  <patente id="106" type="Patente - Invención">
    <title>
      <text lang="es" country="CO">Sistema BDI para el control cooperativo y concurrente de dispositivos robóticos</text>
      </title>
    <description>
      <text lang="es" country="CO">Sistema que controla un robot que responda a imprevistos en un ambiente complejo, tobot de compañia para ancianos. Los robot deben sortear obstaculos mientras interactuan con los humanos</text>
      </description>
    <jurisdiccion>Colombia</jurisdiccion>
    <numeroSolicitud>NC2019/0015039</numeroSolicitud>
    </patente>
  <patente id="109" type="Patente - Invención">
    <title>
      <text lang="es" country="CO">Mecanismo de carga y descarga de materiales para un contenedor</text>
      </title>
    <description>
      <text lang="es" country="CO">Diseño de furgón ergonómico que reduzca al máximo la manipulación manual de cargas y desarrollo de las tareas contempladas dentro del cargue, acomodación de productos y descargue en condiciones postulares que puedan representar un riesgo considerable de generar desordenes musculo esqueléticos o carga cognitiva extraordinaria a los trabajadores durante el desarrollo de la actividad</text>
      </description>
    <jurisdiccion>Colombia</jurisdiccion>
    <numeroSolicitud>NC2019/0010919</numeroSolicitud>
    </patente>
  <patente id="113" type="Patente - Invención">
    <title>
      <text lang="en" country="US">Real time multi agent BDI architecture with agent miogration and methods thereof.</text>
      </title>
    <description>
      <text lang="es" country="CO">Sistema que controla un robot que responda a imprevistos en un ambiente complejo, tobot de compañia para ancianos. Los robot deben sortear obstaculos mientras interactuan con los humanos</text>
      </description>
    <jurisdiccion>Estados Unidos</jurisdiccion>
    <numeroSolicitud>16/652,610</numeroSolicitud>
    </patente>
  <patente id="114" type="Patente - Invención">
    <title>
      <text lang="es" country="CO">Arquitectura de BDI multiagente en tiempo real con migración del agente y métodos de los mismos.</text>
      </title>
    <description>
      <text lang="es" country="CO">Sistema que controla un robot que responda a imprevistos en un ambiente complejo, tobot de compañia para ancianos. Los robot deben sortear obstaculos mientras interactuan con los humanos</text>
      </description>
    <jurisdiccion>Colombia</jurisdiccion>
    <numeroSolicitud>NC2020/0005591</numeroSolicitud>
    </patente>
  <patente id="115" type="Patente - Invención">
    <title>
      <text lang="es" country="CO">Composiciones y métodos para mejorar la actividad de la enzima N-ACETILGALACTOSAMINA-6-SULFATASA y tratar la mucopolisacaridosis tipo IVA</text>
      </title>
    <description>
      <text lang="es" country="CO">Es una proteína que se utiliza para el tratamiento de la enfermedad de morquio, tambipen se usa como parte de una dieta.</text>
      </description>
    <jurisdiccion>Colombia</jurisdiccion>
    <numeroSolicitud>NC2020/0007242</numeroSolicitud>
    </patente>
  <patente id="117" type="Patente - Invención">
    <title>
      <text lang="en" country="US">BDI System for the cooperative and concurrent control of robotic devices</text>
      </title>
    <description>
      <text lang="es" country="CO">Sistema que controla un robot que responda a imprevistos en un ambiente complejo, tobot de compañia para ancianos. Los robot deben sortear obstaculos mientras interactuan con los humanos</text>
      </description>
    <jurisdiccion>Estados Unidos</jurisdiccion>
    <numeroSolicitud>17/138,032</numeroSolicitud>
    </patente>
  <patente id="119" type="Patente - PCT">
    <title>
      <text lang="es" country="CO">Sistema de purificación de agua con luz UV</text>
      </title>
    <description>
      <text lang="es" country="CO">Pure Stream:  consiste en un purificador de agua para la eliminación de bacterias, virus y parásitos. Dicho dispositivo está compuesto por una lámpara excimer de luz Ultravioleta UV (sin mercurio), recubierta por una espiral que guía el agua alrededor de la lámpara para asegurar el tiempo de exposición del agua al UV. La lámpara cuenta con un encendido instantáneo que se activa a la entrada de agua al sistema y disminuye el alto consumo de energía y desperdicio de agua. Es así, que el agua que pasa alrededor o a través de la lámpara se almacena en un reservorio para su uso cuando el usuario la requiera</text>
      </description>
    <jurisdiccion>PCT</jurisdiccion>
    <numeroSolicitud>PCT/IB2021/060428</numeroSolicitud>
    </patente>
  <patente id="120" type="Patente - Invención">
    <title>
      <text lang="en" country="US">P2ET reduces COVID severity by inhibition of viral replication, reduction of pulmonar fibrosis markers and modulation of inmune response</text>
      </title>
    <description>
      <text lang="es" country="CO">Phairilab es un conjunto de invenciones desarrolladas a partir de las propiedades funcionales de las plantas DIvidivi y Anamú que tienen características especiales para desarrollar productos dermocosméticos, suplementos alimenticios  y fitomedicamentos para el tratamiento de pacientes con cancer.</text>
      </description>
    <jurisdiccion>Estados Unidos</jurisdiccion>
    <numeroSolicitud>63292444</numeroSolicitud>
    </patente>
  <patente id="121" type="Patente - Invención">
    <title>
      <text lang="es" country="CO">Kit para la evaluación de ARNM de Trombomodulina en sangre materna para la predicción temprana de la preeclampsia</text>
      </title>
    <description>
      <text lang="es" country="CO">Kit diagnóstico    para     la     predicción temprana de preeclampsia.  A partir  de  una  muestra  de  sangre  de  la  paciente      se      puede      identificar      un      marcador predictivo que está presente en plasma.  Con   el   uso   de   esta   prueba   se   puede   detectar la enfermedad a partir de la de la quinta semana del embarazo, ofreciendo un  manejo  médico  oportuno  tanto  para  la  madre  como  para  el  feto  antes  de  la  aparición      de      los      síntomas,      que      generalmente    sucede    en    la    semana    veinte.</text>
      </description>
    <jurisdiccion>Colombia</jurisdiccion>
    <numeroSolicitud>NC2021/0014590</numeroSolicitud>
    </patente>
  <patente id="122" type="Patente - PCT">
    <title>
      <text lang="es" country="CO">Guia Lineal de Rodillos Compacta</text>
      </title>
    <description>
      <text lang="es" country="CO"> Guia lineal de rodillos compacta que permite transmitir elevadas fuerzas y momentos de torsion entre un carro (1) y un riel de guiado (3). El carro (1) dispone de dos o mas parejas de rodillos acanalados (2), soportados rotativamente en las paredes laterales del carro mediante cojinetes, entre los que se inserta el riel (3) con una seccion transversal complementaria. El contacto simultaneo de las superfices planas y convexas del riel (3) con las superficies cilindricas y concavas de los rodillos (2) permite una distribucion uniforme de las cargas sobre dichos cojinetes y una configuration compacta de la guia.</text>
      </description>
    <jurisdiccion>PCT</jurisdiccion>
    <numeroSolicitud>PCT/IB2011/055465 WO/2013/084024</numeroSolicitud>
    </patente>
  <patente id="123" type="Patente - Invención">
    <title>
      <text lang="pt" country="US">Dispositivo para Toma de Muestras (Saliva)</text>
      </title>
    <description>
      <text lang="es" country="CO">Covid Check: Sistema compuesto por un nuevo set de dispositivo de toma de muestra, primers y sondas con alta sensibilidad y especificidad que permiten cuantificar la carga viral (de diferentes tipos de virus) presente en cada muestra, de una manera más económica, con la obtención de resultados en menor tiempo que se pueda realizar en una muestra corporal de fácil toma como la saliva.</text>
      </description>
    <jurisdiccion>Colombia</jurisdiccion>
    <numeroSolicitud>NC2022/0007774</numeroSolicitud>
    </patente>
  <patente id="125" type="Patente - Invención">
    <title>
      <text lang="en" country="US">Mechanism for Loading and Unloading Materials for a Container</text>
      </title>
    <description>
      <text lang="es" country="CO">Diseño de furgón ergonómico que reduzca al máximo la manipulación manual de cargas y desarrollo de las tareas contempladas dentro del cargue, acomodación de productos y descargue en condiciones postulares que puedan representar un riesgo considerable de generar desordenes musculo esqueléticos o carga cognitiva extraordinaria a los trabajadores durante el desarrollo de la actividad</text>
      </description>
    <jurisdiccion>Estados Unidos</jurisdiccion>
    <numeroSolicitud>17/765,571</numeroSolicitud>
    </patente>
  <patente id="126" type="Patente - Invención">
    <title>
      <text lang="en" country="US">Cosmetic Composition Comprising an Extract of a Microalgae of Galdieria SP. Genus for Cosmetic Applications</text>
      </title>
    <description>
      <text lang="es" country="CO">Formulación cosmética a base del extracto del microalga para aplicación en el cuidado de la piel</text>
      </description>
    <jurisdiccion>Estados Unidos</jurisdiccion>
    <numeroSolicitud>63/336,207</numeroSolicitud>
    </patente>
  <patente id="128" type="Patente - Invención">
    <title>
      <text lang="es" country="CO">"Composiciones y metodos para la protección cognitiva de los polinizadores contra plaguicidas"</text>
      </title>
    <description>
      <text lang="es" country="CO">Es manejada por la Universidad del Rosario. "Composiciones y metodos para la protección cognitiva de los polinizadores contra plaguicidas".Busca proteger a las abejas en contra de los plaguicidas que se utilizan en la agricultura y que no permiten la polinización de las flores.</text>
      </description>
    <jurisdiccion>Colombia</jurisdiccion>
    <numeroSolicitud>NC2022/0004380</numeroSolicitud>
    </patente>
  <patente id="135" type="Patente - Invención">
    <title>
      <text lang="es" country="CO">Proceso de Obtención de un Sucedáneo de Queso Bajo en Sodio con Potencial Funcional, Mediante la Inclusión de Aceite de Palma Alto Oléico</text>
      </title>
    <description>
      <text lang="es" country="CO">Producto y proceso de producción de sucedádenos/análogos ( queso elaborado mediante la sustitución parcial o total de la grasa láctea por grasa vegetal) de queso fresco bajo en sodio con sustitución parcial de la fracción lipídica por aceite hibrido de palma OxG, con el fin de mejorar los acidos grasos respecto a un queso fresco, impactando mínimamente las características de la textura y aceptabilidad sensorial durante su vida útil. Ofrecen queso campesino y queso hilado. Es bueno porque el aceite de palma tiene beneficios para la salud</text>
      </description>
    <jurisdiccion>Colombia</jurisdiccion>
    <numeroSolicitud>NC2022/0013283</numeroSolicitud>
    </patente>
  <patente id="139" type="Marca Nominativa">
    <title>
      <text lang="de" country="US">FOOT LAB (42)</text>
      </title>
    <jurisdiccion>Colombia</jurisdiccion>
    <numeroSolicitud>16070508</numeroSolicitud>
    </patente>
  <patente id="140" type="Marca Nominativa">
    <title>
      <text lang="en" country="US">FASTBACT (1)</text>
      </title>
    <jurisdiccion>Colombia</jurisdiccion>
    <numeroSolicitud>16103199</numeroSolicitud>
    </patente>
  <patente id="141" type="Marca Mixta">
    <title>
      <text lang="vi" country="US">HOMEKO (37)</text>
      </title>
    <description>
      <text lang="es" country="CO">Estructura modular transportable de elementos prefabricados para la construcción de edificaciones. La estructura modular es fabricada con tetrapak, el cual tiene cartón  en su mayoria y otros compuestos</text>
      </description>
    <jurisdiccion>Colombia</jurisdiccion>
    <numeroSolicitud>SD2022/0079149</numeroSolicitud>
    </patente>
  <patente id="143" type="Patente - Invención">
    <title>
      <text lang="en" country="US">Method to Selectively Produce Metabolites from Microalgae of the Genius Galdieria</text>
      </title>
    <description>
      <text lang="es" country="CO">Proceso de manipulación del crecimiento de la microalga Galdieria sp. USBA-GBX 832 para la obtención de un extracto con cantidades interesantes de metabolitos de moléculas complejas, acumulados en la biomasa que poseen capacidades antioxidantes, como también antiangiogénica, citotóxica, anticancerígena, antiobesidad y antimicrobiana.</text>
      </description>
    <jurisdiccion>Estados Unidos</jurisdiccion>
    <numeroSolicitud>18/006,544</numeroSolicitud>
    </patente>
  <patente id="144" type="Patente - PCT">
    <title>
      <text lang="en" country="US">Compositions and Methods for Cognitive Protection of Pollinators Against Pesticides</text>
      </title>
    <description>
      <text lang="es" country="CO">Es manejada por la Universidad del Rosario. "Composiciones y metodos para la protección cognitiva de los polinizadores contra plaguicidas".Busca proteger a las abejas en contra de los plaguicidas que se utilizan en la agricultura y que no permiten la polinización de las flores.</text>
      </description>
    <jurisdiccion>PCT</jurisdiccion>
    <numeroSolicitud>PCT/US2020/049457</numeroSolicitud>
    </patente>
  </patentes>
